{
  "modules": [
    {
      "name": "core",
      "chnname": "核心模块",
      "entities": [
        {
          "title": "user",
          "fields": [
            {
              "name": "id",
              "type": "IdOrKey",
              "remark": "自增主键",
              "chnname": "主键",
              "pk": true,
              "notNull": true,
              "autoIncrement": true
            },
            {
              "name": "username",
              "type": "MiddleString",
              "remark": "",
              "chnname": "用户名称",
              "notNull": true
            },
            {
              "name": "account",
              "type": "ShortString",
              "remark": "",
              "chnname": "登录账号",
              "notNull": true
            },
            {
              "name": "password",
              "type": "ShortString",
              "remark": "sha1加密",
              "chnname": "登录密码",
              "notNull": true,
              "defaultValue": "'7c4a8d09ca3762af61e59520943dc26494f8941b'"
            },
            {
              "name": "is_super",
              "type": "YesNo",
              "remark": "0-否 1-是",
              "chnname": "是否为超级管理员",
              "notNull": true,
              "defaultValue": "0"
            },
            {
              "name": "role",
              "type": "YesNo",
              "remark": "0-超级管理员1-主机管理员2-流量监管员3-日志监管员",
              "chnname": "角色",
              "notNull": true,
              "defaultValue": "0"
            },
            {
              "name": "is_deleted",
              "type": "YesNo",
              "remark": "0-未删除 1-已删除",
              "chnname": "是否删除",
              "notNull": true,
              "defaultValue": "0"
            },
            {
              "name": "created_time",
              "type": "Timestamp",
              "remark": "创建时间",
              "chnname": "创建时间",
              "notNull": true,
              "defaultValue": "current_timestamp"
            },
            {
              "name": "updated_time",
              "type": "Timestamp",
              "remark": "更新时间",
              "chnname": "更新时间",
              "defaultValue": "current_timestamp on update current_timestamp(0)",
              "notNull": true
            }
          ],
          "indexs": [],
          "headers": [
            {
              "fieldName": "chnname",
              "relationNoShow": false
            },
            {
              "fieldName": "name",
              "relationNoShow": false
            },
            {
              "fieldName": "type",
              "relationNoShow": false
            },
            {
              "fieldName": "dataType",
              "relationNoShow": true
            },
            {
              "fieldName": "remark",
              "relationNoShow": true
            },
            {
              "fieldName": "pk",
              "relationNoShow": false
            },
            {
              "fieldName": "notNull",
              "relationNoShow": true
            },
            {
              "fieldName": "autoIncrement",
              "relationNoShow": true
            },
            {
              "fieldName": "defaultValue",
              "relationNoShow": true
            },
            {
              "fieldName": "relationNoShow",
              "relationNoShow": true
            },
            {
              "fieldName": "uiHint",
              "relationNoShow": true
            }
          ],
          "chnname": "用户表"
        },
        {
          "title": "user_session",
          "fields": [
            {
              "name": "id",
              "type": "IdOrKey",
              "remark": "自增主键",
              "chnname": "主键",
              "pk": true,
              "notNull": true,
              "autoIncrement": true
            },
            {
              "name": "user_id",
              "type": "IdOrKey",
              "remark": "对应lawyer表或user表id",
              "chnname": "用户id"
            },
            {
              "name": "session_id",
              "type": "Uuid",
              "remark": "",
              "chnname": "统一认证信息",
              "notNull": true
            },
            {
              "name": "expires_in",
              "type": "BigInt",
              "remark": "单位s，0表示永久有效",
              "chnname": "session有效时间",
              "notNull": true
            },
            {
              "name": "expires_time",
              "type": "BigInt",
              "remark": "0表示永久有效，否则为session过期时间",
              "chnname": "session过期时间"
            },
            {
              "name": "created_time",
              "type": "Timestamp",
              "remark": "创建时间",
              "chnname": "创建时间",
              "notNull": true,
              "defaultValue": "current_timestamp"
            },
            {
              "name": "updated_time",
              "type": "Timestamp",
              "remark": "更新时间",
              "chnname": "更新时间",
              "defaultValue": "current_timestamp on update current_timestamp(0)",
              "notNull": true
            }
          ],
          "indexs": [
            {
              "name": "uk_session_id",
              "isUnique": true,
              "fields": [
                "session_id"
              ]
            }
          ],
          "headers": [
            {
              "fieldName": "chnname",
              "relationNoShow": false
            },
            {
              "fieldName": "name",
              "relationNoShow": false
            },
            {
              "fieldName": "type",
              "relationNoShow": false
            },
            {
              "fieldName": "dataType",
              "relationNoShow": true
            },
            {
              "fieldName": "remark",
              "relationNoShow": true
            },
            {
              "fieldName": "pk",
              "relationNoShow": false
            },
            {
              "fieldName": "notNull",
              "relationNoShow": true
            },
            {
              "fieldName": "autoIncrement",
              "relationNoShow": true
            },
            {
              "fieldName": "defaultValue",
              "relationNoShow": true
            },
            {
              "fieldName": "relationNoShow",
              "relationNoShow": true
            },
            {
              "fieldName": "uiHint",
              "relationNoShow": true
            }
          ],
          "chnname": "用户session表",
          "remark": "用户退出登陆或者session过期，则删除对应记录"
        },
        {
          "title": "white_list",
          "fields": [
            {
              "name": "id",
              "type": "IdOrKey",
              "remark": "自增主键",
              "chnname": "主键",
              "pk": true,
              "notNull": true,
              "autoIncrement": true
            },
            {
              "name": "ip_address",
              "type": "MiddleString",
              "remark": "",
              "chnname": "输入的ip地址信息",
              "notNull": true
            },
            {
              "name": "ip_start",
              "type": "ShortString",
              "remark": "",
              "chnname": "IP段起始地址",
              "notNull": true
            },
            {
              "name": "ip_end",
              "type": "ShortString",
              "remark": "",
              "chnname": "IP段结束地址",
              "notNull": true
            },
            {
              "name": "note",
              "type": "LongString",
              "remark": "",
              "chnname": "备注",
              "notNull": false
            },
            {
              "name": "status",
              "type": "YesNo",
              "remark": "1-正常 2-禁用",
              "chnname": "状态",
              "notNull": true,
              "defaultValue": "1"
            },
            {
              "name": "is_deleted",
              "type": "YesNo",
              "remark": "0-未删除 1-已删除",
              "chnname": "是否删除",
              "notNull": true,
              "defaultValue": "0"
            },
            {
              "name": "created_time",
              "type": "Timestamp",
              "remark": "创建时间",
              "chnname": "创建时间",
              "notNull": true,
              "defaultValue": "current_timestamp"
            },
            {
              "name": "updated_time",
              "type": "Timestamp",
              "remark": "更新时间",
              "chnname": "更新时间",
              "defaultValue": "current_timestamp on update current_timestamp(0)",
              "notNull": true
            }
          ],
          "indexs": [],
          "headers": [
            {
              "fieldName": "chnname",
              "relationNoShow": false
            },
            {
              "fieldName": "name",
              "relationNoShow": false
            },
            {
              "fieldName": "type",
              "relationNoShow": false
            },
            {
              "fieldName": "dataType",
              "relationNoShow": true
            },
            {
              "fieldName": "remark",
              "relationNoShow": true
            },
            {
              "fieldName": "pk",
              "relationNoShow": false
            },
            {
              "fieldName": "notNull",
              "relationNoShow": true
            },
            {
              "fieldName": "autoIncrement",
              "relationNoShow": true
            },
            {
              "fieldName": "defaultValue",
              "relationNoShow": true
            },
            {
              "fieldName": "relationNoShow",
              "relationNoShow": true
            },
            {
              "fieldName": "uiHint",
              "relationNoShow": true
            }
          ],
          "chnname": "白名单"
        },
        {
          "title": "boundary",
          "fields": [
            {
              "name": "id",
              "type": "IdOrKey",
              "remark": "自增主键",
              "chnname": "主键",
              "pk": true,
              "notNull": true,
              "autoIncrement": true
            },
            {
              "name": "ip_address",
              "type": "ShortString",
              "remark": "",
              "chnname": "防火墙IP",
              "notNull": true
            },
            {
              "name": "username",
              "type": "ShortString",
              "remark": "",
              "chnname": "用户名",
              "notNull": true
            },
            {
              "name": "password",
              "type": "ShortString",
              "remark": "",
              "chnname": "密码",
              "notNull": true
            },
            {
              "name": "note",
              "type": "LongString",
              "remark": "",
              "chnname": "备注"
            },
            {
              "name": "status",
              "type": "YesNo",
              "remark": "1-正常 2-禁用",
              "chnname": "状态",
              "notNull": true,
              "defaultValue": "1"
            },
            {
              "name": "is_deleted",
              "type": "YesNo",
              "remark": "0-未删除 1-已删除",
              "chnname": "是否删除",
              "notNull": true,
              "defaultValue": "0"
            },
            {
              "name": "created_time",
              "type": "Timestamp",
              "remark": "创建时间",
              "chnname": "创建时间",
              "notNull": true,
              "defaultValue": "current_timestamp"
            },
            {
              "name": "updated_time",
              "type": "Timestamp",
              "remark": "更新时间",
              "chnname": "更新时间",
              "defaultValue": "current_timestamp on update current_timestamp(0)",
              "notNull": true
            }
          ],
          "indexs": [],
          "headers": [
            {
              "fieldName": "chnname",
              "relationNoShow": false
            },
            {
              "fieldName": "name",
              "relationNoShow": false
            },
            {
              "fieldName": "type",
              "relationNoShow": false
            },
            {
              "fieldName": "dataType",
              "relationNoShow": true
            },
            {
              "fieldName": "remark",
              "relationNoShow": true
            },
            {
              "fieldName": "pk",
              "relationNoShow": false
            },
            {
              "fieldName": "notNull",
              "relationNoShow": true
            },
            {
              "fieldName": "autoIncrement",
              "relationNoShow": true
            },
            {
              "fieldName": "defaultValue",
              "relationNoShow": true
            },
            {
              "fieldName": "relationNoShow",
              "relationNoShow": true
            },
            {
              "fieldName": "uiHint",
              "relationNoShow": true
            }
          ],
          "chnname": "边界表"
        },
        {
          "title": "command",
          "fields": [
            {
              "name": "id",
              "type": "IdOrKey",
              "remark": "自增主键",
              "chnname": "主键",
              "pk": true,
              "notNull": true,
              "autoIncrement": true
            },
            {
              "name": "name",
              "type": "MiddleString",
              "remark": "",
              "chnname": "名称",
              "notNull": true
            },
            {
              "name": "note",
              "type": "LongString",
              "remark": "",
              "chnname": "备注"
            },
            {
              "name": "content",
              "type": "LongString",
              "remark": "",
              "chnname": "命令内容",
              "notNull": true
            },
            {
              "name": "status",
              "type": "YesNo",
              "remark": "1-正常 2-禁用",
              "chnname": "状态",
              "notNull": true,
              "defaultValue": "1"
            },
            {
              "name": "is_deleted",
              "type": "YesNo",
              "remark": "0-未删除 1-已删除",
              "chnname": "是否删除",
              "notNull": true,
              "defaultValue": "0"
            },
            {
              "name": "created_time",
              "type": "Timestamp",
              "remark": "创建时间",
              "chnname": "创建时间",
              "notNull": true,
              "defaultValue": "current_timestamp"
            },
            {
              "name": "updated_time",
              "type": "Timestamp",
              "remark": "更新时间",
              "chnname": "更新时间",
              "defaultValue": "current_timestamp on update current_timestamp(0)",
              "notNull": true
            }
          ],
          "indexs": [],
          "headers": [
            {
              "fieldName": "chnname",
              "relationNoShow": false
            },
            {
              "fieldName": "name",
              "relationNoShow": false
            },
            {
              "fieldName": "type",
              "relationNoShow": false
            },
            {
              "fieldName": "dataType",
              "relationNoShow": true
            },
            {
              "fieldName": "remark",
              "relationNoShow": true
            },
            {
              "fieldName": "pk",
              "relationNoShow": false
            },
            {
              "fieldName": "notNull",
              "relationNoShow": true
            },
            {
              "fieldName": "autoIncrement",
              "relationNoShow": true
            },
            {
              "fieldName": "defaultValue",
              "relationNoShow": true
            },
            {
              "fieldName": "relationNoShow",
              "relationNoShow": true
            },
            {
              "fieldName": "uiHint",
              "relationNoShow": true
            }
          ],
          "chnname": "命令表"
        },
        {
          "title": "perception_source",
          "fields": [
            {
              "name": "id",
              "type": "IdOrKey",
              "remark": "自增主键",
              "chnname": "主键",
              "pk": true,
              "notNull": true,
              "autoIncrement": true
            },
            {
              "name": "name",
              "type": "MiddleString",
              "remark": "",
              "chnname": "平台名称",
              "notNull": true
            },
            {
              "name": "perception_platform",
              "type": "YesNo",
              "remark": "1-深信服 2-绿盟",
              "chnname": "对应平台",
              "notNull": true
            },
            {
              "name": "protocol_type",
              "type": "YesNo",
              "remark": "1-HTTP协议 2-HTTPS协议",
              "chnname": "协议类型",
              "notNull": true
            },
            {
              "name": "host",
              "type": "DefaultString",
              "remark": "",
              "chnname": "主机地址",
              "notNull": true
            },
            {
              "name": "account",
              "type": "ShortString",
              "remark": "",
              "chnname": "登录用户名",
              "notNull": true
            },
            {
              "name": "password",
              "type": "ShortString",
              "remark": "",
              "chnname": "登录密码",
              "notNull": true
            },
            {
              "name": "cookie",
              "type": "LongString",
              "remark": "",
              "chnname": "对应的cookie"
            },
            {
              "name": "is_validated",
              "type": "YesNo",
              "remark": "0-未通过验证 1-已通过验证",
              "chnname": "是否通过验证",
              "notNull": true,
              "defaultValue": "0"
            },
            {
              "name": "extra_data",
              "type": "LongestString",
              "remark": "",
              "chnname": "存储的额外信息"
            },
            {
              "name": "is_deleted",
              "type": "YesNo",
              "remark": "0-未删除 1-已删除",
              "chnname": "是否删除",
              "notNull": true,
              "defaultValue": "0"
            },
            {
              "name": "created_time",
              "type": "Timestamp",
              "remark": "创建时间",
              "chnname": "创建时间",
              "notNull": true,
              "defaultValue": "current_timestamp"
            },
            {
              "name": "updated_time",
              "type": "Timestamp",
              "remark": "更新时间",
              "chnname": "更新时间",
              "defaultValue": "current_timestamp on update current_timestamp(0)",
              "notNull": true
            }
          ],
          "indexs": [],
          "headers": [
            {
              "fieldName": "chnname",
              "relationNoShow": false
            },
            {
              "fieldName": "name",
              "relationNoShow": false
            },
            {
              "fieldName": "type",
              "relationNoShow": false
            },
            {
              "fieldName": "dataType",
              "relationNoShow": true
            },
            {
              "fieldName": "remark",
              "relationNoShow": true
            },
            {
              "fieldName": "pk",
              "relationNoShow": false
            },
            {
              "fieldName": "notNull",
              "relationNoShow": true
            },
            {
              "fieldName": "autoIncrement",
              "relationNoShow": true
            },
            {
              "fieldName": "defaultValue",
              "relationNoShow": true
            },
            {
              "fieldName": "relationNoShow",
              "relationNoShow": true
            },
            {
              "fieldName": "uiHint",
              "relationNoShow": true
            }
          ],
          "chnname": "感知源表"
        },
        {
          "title": "timer",
          "fields": [
            {
              "name": "id",
              "type": "IdOrKey",
              "remark": "自增主键",
              "chnname": "主键",
              "pk": true,
              "notNull": true,
              "autoIncrement": true
            },
            {
              "name": "source_id",
              "type": "IdOrKey",
              "remark": "",
              "chnname": "对应平台",
              "notNull": true
            },
            {
              "name": "cron_express",
              "type": "ShortString",
              "remark": "",
              "chnname": "定时任务表达式",
              "notNull": true
            },
            {
              "name": "status",
              "type": "YesNo",
              "remark": "1-正常 2-禁用",
              "chnname": "定时任务状态",
              "notNull": true,
              "defaultValue": "1"
            },
            {
              "name": "is_deleted",
              "type": "YesNo",
              "remark": "0-未删除 1-已删除",
              "chnname": "是否删除",
              "notNull": true,
              "defaultValue": "0"
            },
            {
              "name": "created_time",
              "type": "Timestamp",
              "remark": "创建时间",
              "chnname": "创建时间",
              "notNull": true,
              "defaultValue": "current_timestamp"
            },
            {
              "name": "updated_time",
              "type": "Timestamp",
              "remark": "更新时间",
              "chnname": "更新时间",
              "defaultValue": "current_timestamp on update current_timestamp(0)",
              "notNull": true
            }
          ],
          "indexs": [],
          "headers": [
            {
              "fieldName": "chnname",
              "relationNoShow": false
            },
            {
              "fieldName": "name",
              "relationNoShow": false
            },
            {
              "fieldName": "type",
              "relationNoShow": false
            },
            {
              "fieldName": "dataType",
              "relationNoShow": true
            },
            {
              "fieldName": "remark",
              "relationNoShow": true
            },
            {
              "fieldName": "pk",
              "relationNoShow": false
            },
            {
              "fieldName": "notNull",
              "relationNoShow": true
            },
            {
              "fieldName": "autoIncrement",
              "relationNoShow": true
            },
            {
              "fieldName": "defaultValue",
              "relationNoShow": true
            },
            {
              "fieldName": "relationNoShow",
              "relationNoShow": true
            },
            {
              "fieldName": "uiHint",
              "relationNoShow": true
            }
          ],
          "chnname": "定时任务表"
        },
        {
          "title": "timer_relation",
          "fields": [
            {
              "name": "id",
              "type": "IdOrKey",
              "remark": "自增主键",
              "chnname": "主键",
              "pk": true,
              "notNull": true,
              "autoIncrement": true
            },
            {
              "name": "timer_id",
              "type": "IdOrKey",
              "remark": "",
              "chnname": "定时任务ID",
              "notNull": true
            },
            {
              "name": "type",
              "type": "YesNo",
              "remark": "1-边界 2-命令",
              "chnname": "关联类型"
            },
            {
              "name": "target_id",
              "type": "IdOrKey",
              "remark": "",
              "chnname": "对应ID",
              "notNull": true
            },
            {
              "name": "is_deleted",
              "type": "YesNo",
              "remark": "0-未删除 1-已删除",
              "chnname": "是否删除",
              "notNull": true,
              "defaultValue": "0"
            },
            {
              "name": "created_time",
              "type": "Timestamp",
              "remark": "创建时间",
              "chnname": "创建时间",
              "notNull": true,
              "defaultValue": "current_timestamp"
            },
            {
              "name": "updated_time",
              "type": "Timestamp",
              "remark": "更新时间",
              "chnname": "更新时间",
              "defaultValue": "current_timestamp on update current_timestamp(0)",
              "notNull": true
            }
          ],
          "indexs": [],
          "headers": [
            {
              "fieldName": "chnname",
              "relationNoShow": false
            },
            {
              "fieldName": "name",
              "relationNoShow": false
            },
            {
              "fieldName": "type",
              "relationNoShow": false
            },
            {
              "fieldName": "dataType",
              "relationNoShow": true
            },
            {
              "fieldName": "remark",
              "relationNoShow": true
            },
            {
              "fieldName": "pk",
              "relationNoShow": false
            },
            {
              "fieldName": "notNull",
              "relationNoShow": true
            },
            {
              "fieldName": "autoIncrement",
              "relationNoShow": true
            },
            {
              "fieldName": "defaultValue",
              "relationNoShow": true
            },
            {
              "fieldName": "relationNoShow",
              "relationNoShow": true
            },
            {
              "fieldName": "uiHint",
              "relationNoShow": true
            }
          ],
          "chnname": "定时任务关联表"
        },
        {
          "title": "attack_source_log",
          "fields": [
            {
              "name": "id",
              "type": "IdOrKey",
              "remark": "自增主键",
              "chnname": "主键",
              "pk": true,
              "notNull": true,
              "autoIncrement": true
            },
            {
              "name": "timer_log_id",
              "type": "IdOrKey",
              "remark": "",
              "chnname": "对应定时任务",
              "notNull": true
            },
            {
              "name": "attack_ip",
              "type": "DefaultString",
              "remark": "",
              "chnname": "攻击ip",
              "notNull": true
            },
            {
              "name": "attack_address",
              "type": "ShortString",
              "remark": "",
              "chnname": "攻击地点",
              "notNull": true
            },
            {
              "name": "attack_number",
              "type": "Integer",
              "remark": "",
              "chnname": "攻击次数",
              "notNull": true
            },
            {
              "name": "attack_type",
              "type": "YesNo",
              "remark": "11-高危攻击（深信服）\n12-残余攻击（深信服）\n13-暴力破解（深信服）\n20-绿盟",
              "chnname": "攻击源类型",
              "notNull": true
            },
            {
              "name": "is_deleted",
              "type": "YesNo",
              "remark": "0-未删除 1-已删除",
              "chnname": "是否删除",
              "notNull": true,
              "defaultValue": "0"
            },
            {
              "name": "created_time",
              "type": "Timestamp",
              "remark": "创建时间",
              "chnname": "创建时间",
              "notNull": true,
              "defaultValue": "current_timestamp"
            },
            {
              "name": "updated_time",
              "type": "Timestamp",
              "remark": "更新时间",
              "chnname": "更新时间",
              "defaultValue": "current_timestamp on update current_timestamp(0)",
              "notNull": true
            }
          ],
          "indexs": [],
          "headers": [
            {
              "fieldName": "chnname",
              "relationNoShow": false
            },
            {
              "fieldName": "name",
              "relationNoShow": false
            },
            {
              "fieldName": "type",
              "relationNoShow": false
            },
            {
              "fieldName": "dataType",
              "relationNoShow": true
            },
            {
              "fieldName": "remark",
              "relationNoShow": true
            },
            {
              "fieldName": "pk",
              "relationNoShow": false
            },
            {
              "fieldName": "notNull",
              "relationNoShow": true
            },
            {
              "fieldName": "autoIncrement",
              "relationNoShow": true
            },
            {
              "fieldName": "defaultValue",
              "relationNoShow": true
            },
            {
              "fieldName": "relationNoShow",
              "relationNoShow": true
            },
            {
              "fieldName": "uiHint",
              "relationNoShow": true
            }
          ],
          "chnname": "攻击源日志"
        },
        {
          "title": "timer_runner_log",
          "fields": [
            {
              "name": "id",
              "type": "IdOrKey",
              "remark": "自增主键",
              "chnname": "主键",
              "pk": true,
              "notNull": true,
              "autoIncrement": true
            },
            {
              "name": "timer_id",
              "type": "IdOrKey",
              "remark": "",
              "chnname": "对应定时任务",
              "notNull": true
            },
            {
              "name": "is_success",
              "type": "YesNo",
              "remark": "0-不成功 1-成功",
              "chnname": "抓取top5是否成功",
              "notNull": true,
              "defaultValue": "0"
            },
            {
              "name": "top5_info",
              "type": "LongestString",
              "remark": "",
              "chnname": "top5信息"
            },
            {
              "name": "command_number",
              "type": "Integer",
              "remark": "",
              "chnname": "待执行命令条数",
              "notNull": true,
              "defaultValue": "0"
            },
            {
              "name": "command_success_number",
              "type": "Integer",
              "remark": "",
              "chnname": "执行命令成功条数",
              "notNull": true,
              "defaultValue": "0"
            },
            {
              "name": "is_deleted",
              "type": "YesNo",
              "remark": "0-未删除 1-已删除",
              "chnname": "是否删除",
              "notNull": true,
              "defaultValue": "0"
            },
            {
              "name": "created_time",
              "type": "Timestamp",
              "remark": "创建时间",
              "chnname": "创建时间",
              "notNull": true,
              "defaultValue": "current_timestamp"
            },
            {
              "name": "updated_time",
              "type": "Timestamp",
              "remark": "更新时间",
              "chnname": "更新时间",
              "defaultValue": "current_timestamp on update current_timestamp(0)",
              "notNull": true
            }
          ],
          "indexs": [],
          "headers": [
            {
              "fieldName": "chnname",
              "relationNoShow": false
            },
            {
              "fieldName": "name",
              "relationNoShow": false
            },
            {
              "fieldName": "type",
              "relationNoShow": false
            },
            {
              "fieldName": "dataType",
              "relationNoShow": true
            },
            {
              "fieldName": "remark",
              "relationNoShow": true
            },
            {
              "fieldName": "pk",
              "relationNoShow": false
            },
            {
              "fieldName": "notNull",
              "relationNoShow": true
            },
            {
              "fieldName": "autoIncrement",
              "relationNoShow": true
            },
            {
              "fieldName": "defaultValue",
              "relationNoShow": true
            },
            {
              "fieldName": "relationNoShow",
              "relationNoShow": true
            },
            {
              "fieldName": "uiHint",
              "relationNoShow": true
            }
          ],
          "chnname": "定时任务执行日志"
        },
        {
          "title": "timer_command_log",
          "fields": [
            {
              "name": "id",
              "type": "IdOrKey",
              "remark": "自增主键",
              "chnname": "主键",
              "pk": true,
              "notNull": true,
              "autoIncrement": true
            },
            {
              "name": "timer_log_id",
              "type": "IdOrKey",
              "remark": "",
              "chnname": "定时任务运行ID",
              "notNull": true
            },
            {
              "name": "boundary_id",
              "type": "IdOrKey",
              "remark": "",
              "chnname": "对应边界ID",
              "notNull": true
            },
            {
              "name": "command_id",
              "type": "IdOrKey",
              "remark": "",
              "chnname": "对应命令ID",
              "notNull": true
            },
            {
              "name": "ip_address",
              "type": "DefaultString",
              "remark": "",
              "chnname": "对应IP",
              "notNull": true
            },
            {
              "name": "is_white",
              "type": "YesNo",
              "remark": "是否为白名单IP：0-否 1-是",
              "chnname": "是否为白名单",
              "notNull": true,
              "defaultValue": "0"
            },
            {
              "name": "command_content",
              "type": "LongestString",
              "remark": "",
              "chnname": "执行命令内容",
              "notNull": true
            },
            {
              "name": "is_success",
              "type": "YesNo",
              "remark": "",
              "chnname": "是否成功",
              "notNull": true,
              "defaultValue": "0"
            },
            {
              "name": "command_result",
              "type": "LongestString",
              "remark": "",
              "chnname": "返回结果"
            },
            {
              "name": "err_msg",
              "type": "LongString",
              "remark": "",
              "chnname": "错误信息"
            },
            {
              "name": "is_deleted",
              "type": "YesNo",
              "remark": "0-未删除 1-已删除",
              "chnname": "是否删除",
              "notNull": true,
              "defaultValue": "0"
            },
            {
              "name": "created_time",
              "type": "Timestamp",
              "remark": "创建时间",
              "chnname": "创建时间",
              "notNull": true,
              "defaultValue": "current_timestamp"
            },
            {
              "name": "updated_time",
              "type": "Timestamp",
              "remark": "更新时间",
              "chnname": "更新时间",
              "defaultValue": "current_timestamp on update current_timestamp(0)",
              "notNull": true
            }
          ],
          "indexs": [],
          "headers": [
            {
              "fieldName": "chnname",
              "relationNoShow": false
            },
            {
              "fieldName": "name",
              "relationNoShow": false
            },
            {
              "fieldName": "type",
              "relationNoShow": false
            },
            {
              "fieldName": "dataType",
              "relationNoShow": true
            },
            {
              "fieldName": "remark",
              "relationNoShow": true
            },
            {
              "fieldName": "pk",
              "relationNoShow": false
            },
            {
              "fieldName": "notNull",
              "relationNoShow": true
            },
            {
              "fieldName": "autoIncrement",
              "relationNoShow": true
            },
            {
              "fieldName": "defaultValue",
              "relationNoShow": true
            },
            {
              "fieldName": "relationNoShow",
              "relationNoShow": true
            },
            {
              "fieldName": "uiHint",
              "relationNoShow": true
            }
          ],
          "chnname": "定时任务执行命令记录表"
        },
        {
          "title": "shreshold",
          "fields": [
            {
              "name": "id",
              "type": "IdOrKey",
              "remark": "自增主键",
              "chnname": "主键",
              "pk": true,
              "notNull": true,
              "autoIncrement": true
            },
            {
              "name": "name",
              "type": "ShortString",
              "remark": "",
              "chnname": "名称"
            },
            {
              "name": "key",
              "type": "ShortString",
              "remark": "",
              "chnname": "键"
            },
            {
              "name": "value",
              "type": "DefaultString",
              "remark": "",
              "chnname": "值"
            },
            {
              "name": "is_deleted",
              "type": "YesNo",
              "remark": "0-未删除 1-已删除",
              "chnname": "是否删除",
              "notNull": true,
              "defaultValue": "0"
            },
            {
              "name": "created_time",
              "type": "Timestamp",
              "remark": "创建时间",
              "chnname": "创建时间",
              "notNull": true,
              "defaultValue": "current_timestamp"
            },
            {
              "name": "updated_time",
              "type": "Timestamp",
              "remark": "更新时间",
              "chnname": "更新时间",
              "defaultValue": "current_timestamp on update current_timestamp(0)",
              "notNull": true
            }
          ],
          "indexs": [],
          "headers": [
            {
              "fieldName": "chnname",
              "relationNoShow": false
            },
            {
              "fieldName": "name",
              "relationNoShow": false
            },
            {
              "fieldName": "type",
              "relationNoShow": false
            },
            {
              "fieldName": "dataType",
              "relationNoShow": true
            },
            {
              "fieldName": "remark",
              "relationNoShow": true
            },
            {
              "fieldName": "pk",
              "relationNoShow": false
            },
            {
              "fieldName": "notNull",
              "relationNoShow": true
            },
            {
              "fieldName": "autoIncrement",
              "relationNoShow": true
            },
            {
              "fieldName": "defaultValue",
              "relationNoShow": true
            },
            {
              "fieldName": "relationNoShow",
              "relationNoShow": true
            },
            {
              "fieldName": "uiHint",
              "relationNoShow": true
            }
          ],
          "chnname": "阈值配置"
        }
      ],
      "graphCanvas": {
        "nodes": [],
        "edges": []
      },
      "associations": []
    }
  ],
  "dataTypeDomains": {
    "datatype": [
      {
        "name": "主键",
        "code": "IdOrKey",
        "apply": {
          "JAVA": {
            "type": ""
          },
          "ORACLE": {
            "type": ""
          },
          "MYSQL": {
            "type": "bigint(20) unsigned"
          },
          "SQLServer": {
            "type": ""
          },
          "PostgreSQL": {
            "type": ""
          }
        }
      },
      {
        "name": "枚举类型",
        "code": "YesNo",
        "apply": {
          "JAVA": {
            "type": "int"
          },
          "MYSQL": {
            "type": "tinyint(2) unsigned"
          },
          "ORACLE": {
            "type": ""
          },
          "SQLServer": {
            "type": ""
          },
          "PostgreSQL": {
            "type": ""
          }
        }
      },
      {
        "name": "标识号-uuid",
        "code": "Uuid",
        "apply": {
          "MYSQL": {
            "type": "varchar(32)"
          },
          "ORACLE": {
            "type": "VARCHAR2(32)"
          },
          "JAVA": {
            "type": "String"
          },
          "SQLServer": {
            "type": "VARCHAR(32)"
          },
          "PostgreSQL": {
            "type": "VARCHAR(32)"
          }
        }
      },
      {
        "name": "字符串-10",
        "code": "MinestString",
        "apply": {
          "MYSQL": {
            "type": "varchar(10)"
          },
          "ORACLE": {
            "type": ""
          },
          "JAVA": {
            "type": "String"
          },
          "SQLServer": {
            "type": ""
          },
          "PostgreSQL": {
            "type": ""
          }
        }
      },
      {
        "name": "字符串-20",
        "code": "DefaultString",
        "apply": {
          "JAVA": {
            "type": "String"
          },
          "MYSQL": {
            "type": "varchar(32)"
          },
          "ORACLE": {
            "type": "NVARCHAR2(32)"
          },
          "SQLServer": {
            "type": "NVARCHAR(32)"
          },
          "PostgreSQL": {
            "type": "VARCHAR(32)"
          }
        }
      },
      {
        "name": "字符串-50",
        "code": "ShortString",
        "apply": {
          "JAVA": {
            "type": "String"
          },
          "MYSQL": {
            "type": "varchar(50)"
          },
          "ORACLE": {
            "type": ""
          },
          "SQLServer": {
            "type": ""
          },
          "PostgreSQL": {
            "type": ""
          }
        }
      },
      {
        "name": "字符串-128",
        "code": "MiddleString",
        "apply": {
          "JAVA": {
            "type": "String"
          },
          "MYSQL": {
            "type": "varchar(128)"
          },
          "ORACLE": {
            "type": ""
          },
          "SQLServer": {
            "type": ""
          },
          "PostgreSQL": {
            "type": ""
          }
        }
      },
      {
        "name": "字符串-255",
        "code": "LongString",
        "apply": {
          "JAVA": {
            "type": "String"
          },
          "ORACLE": {
            "type": "NVARCHAR2(255)"
          },
          "MYSQL": {
            "type": "varchar(255)"
          },
          "SQLServer": {
            "type": "NVARCHAR(255)"
          },
          "PostgreSQL": {
            "type": "VARCHAR(255)"
          }
        }
      },
      {
        "name": "字符串-3072",
        "code": "LongestString",
        "apply": {
          "JAVA": {
            "type": "String"
          },
          "ORACLE": {
            "type": "NVARCHAR2(3072)"
          },
          "MYSQL": {
            "type": "varchar(3072)"
          },
          "SQLServer": {
            "type": "NVARCHAR(3072)"
          },
          "PostgreSQL": {
            "type": "VARCHAR(3072)"
          }
        }
      },
      {
        "name": "文本",
        "code": "text",
        "apply": {
          "JAVA": {
            "type": "String"
          },
          "MYSQL": {
            "type": "text"
          },
          "ORACLE": {
            "type": ""
          },
          "SQLServer": {
            "type": ""
          },
          "PostgreSQL": {
            "type": ""
          }
        }
      },
      {
        "name": "大文本",
        "code": "LongText",
        "apply": {
          "JAVA": {
            "type": "String"
          },
          "MYSQL": {
            "type": "longtext"
          },
          "ORACLE": {
            "type": ""
          },
          "SQLServer": {
            "type": ""
          },
          "PostgreSQL": {
            "type": ""
          }
        }
      },
      {
        "name": "整数",
        "code": "Integer",
        "apply": {
          "JAVA": {
            "type": "Integer"
          },
          "MYSQL": {
            "type": "int"
          },
          "ORACLE": {
            "type": "INT"
          },
          "SQLServer": {
            "type": "INT"
          },
          "PostgreSQL": {
            "type": "INT"
          }
        }
      },
      {
        "name": "大整数",
        "code": "BigInt",
        "apply": {
          "MYSQL": {
            "type": "bigint(20)"
          },
          "JAVA": {
            "type": "Long"
          },
          "ORACLE": {
            "type": "NUMBER"
          },
          "SQLServer": {
            "type": "BIGINT"
          },
          "PostgreSQL": {
            "type": "BIGINT"
          }
        }
      },
      {
        "name": "金额",
        "code": "Money",
        "apply": {
          "JAVA": {
            "type": "Double"
          },
          "MYSQL": {
            "type": "decimal(32,8)"
          },
          "ORACLE": {
            "type": "NUMBER(32,8)"
          },
          "SQLServer": {
            "type": "DECIMAL(32,8)"
          },
          "PostgreSQL": {
            "type": "DECIMAL(32,8)"
          }
        }
      },
      {
        "name": "时间戳",
        "code": "Timestamp",
        "apply": {
          "JAVA": {
            "type": ""
          },
          "MYSQL": {
            "type": "timestamp"
          },
          "ORACLE": {
            "type": ""
          },
          "SQLServer": {
            "type": ""
          },
          "PostgreSQL": {
            "type": ""
          }
        }
      },
      {
        "name": "日期",
        "code": "Date",
        "apply": {
          "JAVA": {
            "type": "Date"
          },
          "MYSQL": {
            "type": "date"
          },
          "ORACLE": {
            "type": "DATE"
          },
          "SQLServer": {
            "type": "DATE"
          },
          "PostgreSQL": {
            "type": "DATE"
          }
        }
      },
      {
        "name": "日期时间",
        "code": "DateTime",
        "apply": {
          "JAVA": {
            "type": "Date"
          },
          "MYSQL": {
            "type": "datetime"
          },
          "ORACLE": {
            "type": "DATE"
          },
          "SQLServer": {
            "type": "DATE"
          },
          "PostgreSQL": {
            "type": "DATETIME"
          }
        }
      }
    ],
    "database": [
      {
        "code": "MYSQL",
        "template": "DROP TABLE {{=it.entity.title}};\n$blankline\nCREATE TABLE {{=it.entity.title}}(\n{{ pkList = [] ; }}\n{{~it.entity.fields:field:index}}\n    {{? field.pk }}{{ pkList.push(field.name) }}{{?}}\n    {{=field.name}} {{=field.type}} {{= field.pk ? 'NOT NULL' : '' }} COMMENT '{{=it.func.join(field.chnname,field.remark,';')}}' {{= index < it.entity.fields.length-1 ? ',' : ( pkList.length>0 ? ',' :'' ) }}\n{{~}}\n{{? pkList.length >0 }}\n    PRIMARY KEY ({{~pkList:pkName:i}}{{= pkName }}{{= i<pkList.length-1 ? ',' : '' }}{{~}})\n{{?}}\n) COMMENT = '{{=it.func.join(it.entity.chnname,it.entity.remark,';') }}'",
        "fileShow": true,
        "defaultDatabase": true,
        "createTableTemplate": "CREATE TABLE {{=it.entity.title}}(\n{{ pkList = [] ; }}\n{{~it.entity.fields:field:index}}\n    {{? field.pk }}{{ pkList.push(field.name) }}{{?}}\n    {{=field.name}} {{=field.type}} {{= field.notNull ? 'NOT NULL' : '' }} {{= field.autoIncrement ? 'AUTO_INCREMENT' : '' }} {{= field.defaultValue ? it.func.join('DEFAULT',field.defaultValue,' ') : '' }} COMMENT '{{=it.func.join(field.chnname,field.remark,' ')}}' {{= index < it.entity.fields.length-1 ? ',' : ( pkList.length>0 ? ',' :'' ) }}\n{{~}}\n{{? pkList.length >0 }}\n    PRIMARY KEY ({{~pkList:pkName:i}}{{= pkName }}{{= i<pkList.length-1 ? ',' : '' }}{{~}})\n{{?}}\n) COMMENT = '{{=it.func.join(it.entity.chnname,it.entity.remark,' ') }}';{{=it.separator}}\n$blankline\n",
        "deleteTableTemplate": "DROP TABLE {{=it.entity.title}};{{=it.separator}}/*SkipError*/",
        "rebuildTableTemplate": "create table PDMAN_UP_{{=it.oldEntity.title}}\nas select * from {{=it.oldEntity.title}};{{=it.separator}}\n$blankline\n\ndrop table {{=it.oldEntity.title}};{{=it.separator}}\n$blankline\n\nCREATE TABLE {{=it.newEntity.title}}(\n{{ pkList = [] ; }}\n{{~it.newEntity.fields:field:index}}\n    {{? field.pk }}{{ pkList.push(field.name) }}{{?}}\n    {{=field.name}} {{=field.type}} {{= field.notNull ? 'NOT NULL' : '' }} COMMENT '{{=it.func.join(field.chnname,field.remark,';')}}' {{= index < it.newEntity.fields.length-1 ? ',' : ( pkList.length>0 ? ',' :'' ) }}\n{{~}}\n{{? pkList.length >0 }}\n    PRIMARY KEY ({{~pkList:pkName:i}}{{= pkName }}{{= i<pkList.length-1 ? ',' : '' }}{{~}})\n{{?}}\n) COMMENT = '{{=it.func.join(it.newEntity.chnname,it.newEntity.remark,';') }}';{{=it.separator}}\n$blankline\n\n{{ sameCols = it.func.intersect(it.newEntity.fields,it.oldEntity.fields) ;}}\ninsert into {{=it.newEntity.title}}(\n{{~sameCols:field:index}}\n    {{=field.name}}{{? index<sameCols.length-1}},{{?}}\n{{~}}\n) \nselect \n{{~sameCols:field:index}}\n    {{=field.name}}{{? index<sameCols.length-1}},{{?}}\n{{~}}\nfrom PDMAN_UP_{{=it.oldEntity.title}};{{=it.separator}}\n$blankline\n\ndrop table PDMAN_UP_{{=it.oldEntity.title}};{{=it.separator}}\n$blankline\n{{~it.newEntity.indexs:index}}\nALTER TABLE {{=it.newEntity.title}} ADD {{? index.isUnique}}UNIQUE{{??}}INDEX{{?}} {{=index.name}}({{=it.func.join(...index.fields,',')}});{{=it.separator}}\n{{~}}",
        "createFieldTemplate": "ALTER TABLE {{=it.entity.title}} ADD COLUMN {{=it.field.name}} {{=it.field.type}} {{? it.field.notNull}}NOT NULL{{?}} {{? it.field.defaultValue}}DEFAULT {{? null==it.field.defaultValue}}NULL{{??}}'{{=it.field.defaultValue}}'{{?}}{{?}} {{? it.field.autoIncrement}}AUTO_INCREMENT{{?}} {{? it.field.pk}}PRIMARY KEY{{?}} {{? it.field.chnname}}COMMENT '{{=it.field.chnname}}'{{?}} {{? it.field.addAfter}}AFTER {{=it.field.addAfter}}{{?}};{{=it.separator}}",
        "updateFieldTemplate": "ALTER TABLE {{=it.entity.title}} MODIFY COLUMN {{=it.field.name}} {{=it.field.type}} {{? it.field.notNull}}NOT NULL{{?}} {{? it.field.defaultValue}}DEFAULT {{? null==it.field.defaultValue}}NULL{{??}}'{{=it.field.defaultValue}}'{{?}}{{?}} {{? it.field.autoIncrement}}AUTO_INCREMENT{{?}} {{? it.field.chnname}}COMMENT '{{=it.field.chnname}}'{{?}};{{=it.separator}}",
        "deleteFieldTemplate": "ALTER TABLE {{=it.entity.title}} DROP {{=it.field.name}};{{=it.separator}}",
        "deleteIndexTemplate": "ALTER TABLE {{=it.entity.title}} DROP INDEX {{=it.index.name}};{{=it.separator}}",
        "createIndexTemplate": "ALTER TABLE {{=it.entity.title}} ADD {{? it.index.isUnique}}UNIQUE{{??}}INDEX{{?}} {{=it.index.name}}({{=it.func.join(...it.index.fields,',')}});{{=it.separator}}",
        "updateTableComment": "ALTER TABLE {{=it.entity.title}} COMMENT '{{=it.entity.chnname}}';{{=it.separator}}"
      },
      {
        "code": "ORACLE",
        "template": "DROP TABLE {{=it.entity.title}};{{=it.separator}}\n$blankline\nCREATE TABLE {{=it.entity.title}}(\n{{ pkList = [] ; }}\n{{~it.entity.fields:field:index}}\n    {{? field.pk }}{{ pkList.push(field.name) }}{{?}}\n    {{=field.name}} {{=field.type}}  {{= field.pk ? 'NOT NULL' : '' }} {{= index < it.entity.fields.length-1 ? ',' : ( pkList.length>0 ? ',' :'' ) }}\n{{~}}\n{{? pkList.length >0 }}\n    PRIMARY KEY ({{~pkList:pkName:i}}{{= pkName }}{{= i<pkList.length-1 ? ',' : '' }}{{~}})\n{{?}}\n);{{=it.separator}}\n$blankline\nCOMMENT ON TABLE {{=it.entity.title}} IS '{{=it.func.join(it.entity.chnname,it.entity.remark,';') }}';{{=it.separator}}\n{{~it.entity.fields:field:index}}\nCOMMENT ON COLUMN {{=it.entity.title}}.{{=field.name}} IS '{{=it.func.join(field.chnname,field.remark,';')}}';{{=it.separator}}\n{{~}}",
        "createTableTemplate": "CREATE TABLE {{=it.entity.title}}(\n{{ pkList = [] ; }}\n{{~it.entity.fields:field:index}}\n    {{? field.pk }}{{ pkList.push(field.name) }}{{?}}\n    {{=field.name}} {{=field.type}}{{? field.defaultValue}} DEFAULT {{=field.defaultValue}}{{?}}{{= field.notNull ? ' NOT NULL' : '' }}{{= index < it.entity.fields.length-1 ? ',' : ( pkList.length>0 ? ',' :'' ) }}\n{{~}}\n{{? pkList.length >0 }}\n    PRIMARY KEY ({{~pkList:pkName:i}}{{= pkName }}{{= i<pkList.length-1 ? ',' : '' }}{{~}})\n{{?}}\n);{{=it.separator}}\n$blankline\n{{? it.entity.chnname || it.entity.remark}}COMMENT ON TABLE {{=it.entity.title}} IS {{? it.entity.remark}}'{{=it.entity.remark}}'{{??}}'{{=it.entity.chnname}}'{{?}};{{=it.separator}}{{?}}\n{{~it.entity.fields:field:index}}\n{{? field.chnname || field.remark}}COMMENT ON COLUMN {{=it.entity.title}}.{{=field.name}} IS {{? field.remark}}'{{=field.remark}}'{{??}}'{{=field.chnname}}'{{?}};{{=it.separator}}{{?}}\n{{~}}",
        "deleteTableTemplate": "DROP TABLE {{=it.entity.title}};{{=it.separator}}/*SkipError*/\r\n$blankline",
        "rebuildTableTemplate": "CREATE TABLE PDMAN_UP_{{=it.oldEntity.title}}\nAS SELECT * FROM {{=it.oldEntity.title}};{{=it.separator}}\n$blankline\nDROP TABLE {{=it.oldEntity.title}};{{=it.separator}}\n$blankline\nCREATE TABLE {{=it.newEntity.title}}(\n{{ pkList = [] ; }}{{~it.newEntity.fields:field:index}}{{? field.pk }}{{ pkList.push(field.name) }}{{?}}    {{=field.name}} {{=field.type}}{{? field.defaultValue}} DEFAULT {{=field.defaultValue}}{{?}}{{= field.notNull ? ' NOT NULL' : '' }}{{= index < it.newEntity.fields.length-1 ? ',' : ( pkList.length>0 ? ',' :'' ) }}\n{{~}}{{? pkList.length >0 }}    PRIMARY KEY ({{~pkList:pkName:i}}{{= pkName }}{{= i<pkList.length-1 ? ',' : '' }}{{~}}){{?}}\n);{{=it.separator}}\n$blankline\n{{? it.newEntity.chnname || it.newEntity.remark}}COMMENT ON TABLE {{=it.newEntity.title}} IS {{? it.newEntity.remark}}'{{=it.entity.remark}}'{{??}}'{{=it.newEntity.chnname}}'{{?}};{{?}}{{=it.separator}}\n{{~it.newEntity.fields:field:index}}\n{{? field.chnname || field.remark}}COMMENT ON COLUMN {{=it.newEntity.title}}.{{=field.name}} IS {{? field.remark}}'{{=field.remark}}'{{??}}'{{=field.chnname}}'{{?}};{{?}}{{=it.separator}}\n{{~}}\n{{ sameCols = it.func.intersect(it.newEntity.fields,it.oldEntity.fields) ;}}\n$blankline\nINSERT INTO {{=it.newEntity.title}}(\n{{~sameCols:field:index}}   {{=field.name}}{{? index<sameCols.length-1}},{{?}}\n{{~}}) \nSELECT\n{{~sameCols:field:index}}   {{=field.name}}{{? index<sameCols.length-1}},{{?}}\n{{~}}FROM PDMAN_UP_{{=it.oldEntity.title}};{{=it.separator}}\n\nDROP TABLE PDMAN_UP_{{=it.oldEntity.title}};{{=it.separator}}\n{{~it.newEntity.indexs:index}}\nCREATE{{? index.isUnique}} UNIQUE{{?}} INDEX {{=index.name}} ON {{=it.newEntity.title}}({{=it.func.join(index.fields,',')}});{{=it.separator}}\n{{~}}",
        "createFieldTemplate": "ALTER TABLE {{=it.entity.title}} ADD({{=it.field.name}} {{=it.field.type}}{{? it.field.defaultValue}} DEFAULT {{=it.field.defaultValue}}{{?}}{{? it.field.notNull}} NOT NULL{{?}});{{=it.separator}}\r\n{{? it.field.chnname || it.field.remark}}COMMENT ON COLUMN {{=it.entity.title}}.{{=it.field.name}} IS {{? it.field.remark}}'{{=it.field.remark}}'{{??}}'{{=it.field.chnname}}'{{?}};{{=it.separator}}{{?}}\r\n$blankline",
        "updateFieldTemplate": "ALTER TABLE {{=it.entity.title}} MODIFY({{=it.field.name}} {{=it.field.type}}{{? it.field.defaultValue}} DEFAULT {{=it.field.defaultValue}}{{?}}{{? it.field.notNull}} NOT NULL{{?}});{{=it.separator}}\r\n{{? it.field.chnname || it.field.remark}}COMMENT ON COLUMN {{=it.entity.title}}.{{=it.field.name}} IS {{? it.field.remark}}'{{=it.field.remark}}'{{??}}'{{=it.field.chnname}}'{{?}};{{=it.separator}}{{=it.separator}}{{?}}\r\n$blankline",
        "deleteFieldTemplate": "ALTER TABLE {{=it.entity.title}} DROP({{=it.field.name}});{{=it.separator}}\r\n$blankline",
        "deleteIndexTemplate": "DROP INDEX {{=it.entity.title}}.{{=it.index.name}};{{=it.separator}}\r\n$blankline",
        "createIndexTemplate": "CREATE{{? it.index.isUnique}} UNIQUE{{?}} INDEX {{=it.index.name}} ON {{=it.entity.title}}({{=it.func.join(it.index.fields,',')}});{{=it.separator}}\r\n$blankline",
        "updateTableComment": "{{? it.entity.chnname || it.entity.remark}}COMMENT ON TABLE {{=it.entity.title}} IS {{? it.entity.remark}}'{{=it.entity.remark}}'{{??}}'{{=it.entity.chnname}}'{{?}};{{=it.separator}}{{?}}\r\n$blankline"
      },
      {
        "code": "SQLServer",
        "createTableTemplate": "CREATE TABLE {{=it.entity.title}}(\n{{ pkList = [] ; }}\n{{~it.entity.fields:field:index}}\n    {{? field.pk }}{{ pkList.push(field.name) }}{{?}}\n    {{=field.name}} {{=field.type}} {{= field.notNull ? 'NOT NULL' : '' }} {{= field.autoIncrement ? 'IDENTITY(1,1)' : '' }} {{= field.defaultValue ? it.func.join('DEFAULT',field.defaultValue,' ') : '' }}  {{= index < it.entity.fields.length-1 ? ',' : ( pkList.length>0 ? ',' :'' ) }}\n{{~}}\n{{? pkList.length >0 }}\n    CONSTRAINT PK_{{=it.entity.title}} PRIMARY KEY CLUSTERED ({{~pkList:pkName:i}}{{= pkName }} ASC {{= i<pkList.length-1 ? ',' : '' }}{{~}}) ON [PRIMARY] \n{{?}}\n) ;{{=it.separator}}\n\n$blankline\nEXECUTE sp_addextendedproperty N'MS_Description', '{{= it.entity.chnname || it.entity.remark}}', N'user', N'dbo', N'table', N'{{=it.entity.title}}', NULL, NULL;{{=it.separator}}\n{{~it.entity.fields:field:index}}\n{{? field.chnname || field.remark}}EXECUTE sp_addextendedproperty N'MS_Description', {{? field.remark}}'{{=field.remark}}'{{??}}'{{=field.chnname}}'{{?}}, N'user', N'dbo', N'table', N'{{=it.entity.title}}', N'column', N'{{=field.name}}';{{=it.separator}}{{?}}\n{{~}}\n",
        "deleteTableTemplate": "",
        "rebuildTableTemplate": "",
        "createFieldTemplate": "",
        "updateFieldTemplate": "",
        "deleteFieldTemplate": "",
        "deleteIndexTemplate": "",
        "createIndexTemplate": "",
        "updateTableComment": ""
      },
      {
        "code": "PostgreSQL",
        "template": "DROP TABLE {{=it.entity.title}};\n$blankline\nCREATE TABLE {{=it.entity.title}}(\n{{ pkList = [] ; }}\n{{~it.entity.fields:field:index}}\n    {{? field.pk }}{{ pkList.push(field.name) }}{{?}}\n    {{=field.name}} {{=field.type}} {{= field.pk ? 'NOT NULL' : '' }} COMMENT '{{=it.func.join(field.chnname,field.remark,';')}}' {{= index < it.entity.fields.length-1 ? ',' : ( pkList.length>0 ? ',' :'' ) }}\n{{~}}\n{{? pkList.length >0 }}\n    PRIMARY KEY ({{~pkList:pkName:i}}{{= pkName }}{{= i<pkList.length-1 ? ',' : '' }}{{~}})\n{{?}}\n) COMMENT = '{{=it.func.join(it.entity.chnname,it.entity.remark,';') }}'",
        "createTableTemplate": "CREATE TABLE {{=it.entity.title}}(\n{{ pkList = [] ; }}\n{{~it.entity.fields:field:index}}\n    {{? field.pk }}{{ pkList.push(field.name) }}{{?}}\n    {{=field.name}} {{=field.type}}{{? field.defaultValue}} DEFAULT {{=field.defaultValue}}{{?}}{{= field.notNull ? ' NOT NULL' : '' }}{{= index < it.entity.fields.length-1 ? ',' : ( pkList.length>0 ? ',' :'' ) }}\n{{~}}\n{{? pkList.length >0 }}\n    PRIMARY KEY ({{~pkList:pkName:i}}{{= pkName }}{{= i<pkList.length-1 ? ',' : '' }}{{~}})\n{{?}}\n);{{=it.separator}}\n$blankline\n{{? it.entity.chnname || it.entity.remark}}COMMENT ON TABLE {{=it.entity.title}} IS {{? it.entity.remark}}'{{=it.entity.remark}}'{{??}}'{{=it.entity.chnname}}'{{?}};{{=it.separator}}{{?}}\n{{~it.entity.fields:field:index}}\n{{? field.chnname || field.remark}}COMMENT ON COLUMN {{=it.entity.title}}.{{=field.name}} IS {{? field.remark}}'{{=field.remark}}'{{??}}'{{=field.chnname}}'{{?}};{{=it.separator}}{{?}}\n{{~}}",
        "deleteTableTemplate": "DROP TABLE {{=it.entity.title}};{{=it.separator}}/*SkipError*/",
        "rebuildTableTemplate": "create table PDMAN_UP_{{=it.oldEntity.title}}\nas select * from {{=it.oldEntity.title}};{{=it.separator}}\n$blankline\n\ndrop table {{=it.oldEntity.title}};{{=it.separator}}\n$blankline\n\nCREATE TABLE {{=it.newEntity.title}}(\n{{ pkList = [] ; }}\n{{~it.newEntity.fields:field:index}}\n    {{? field.pk }}{{ pkList.push(field.name) }}{{?}}\n    {{=field.name}} {{=field.type}} {{= field.notNull ? 'NOT NULL' : '' }} COMMENT '{{=it.func.join(field.chnname,field.remark,';')}}' {{= index < it.newEntity.fields.length-1 ? ',' : ( pkList.length>0 ? ',' :'' ) }}\n{{~}}\n{{? pkList.length >0 }}\n    PRIMARY KEY ({{~pkList:pkName:i}}{{= pkName }}{{= i<pkList.length-1 ? ',' : '' }}{{~}})\n{{?}}\n) COMMENT = '{{=it.func.join(it.newEntity.chnname,it.newEntity.remark,';') }}';{{=it.separator}}\n$blankline\n\n{{ sameCols = it.func.intersect(it.newEntity.fields,it.oldEntity.fields) ;}}\ninsert into {{=it.newEntity.title}}(\n{{~sameCols:field:index}}\n    {{=field.name}}{{? index<sameCols.length-1}},{{?}}\n{{~}}\n) \nselect \n{{~sameCols:field:index}}\n    {{=field.name}}{{? index<sameCols.length-1}},{{?}}\n{{~}}\nfrom PDMAN_UP_{{=it.oldEntity.title}};{{=it.separator}}\n$blankline\n\ndrop table PDMAN_UP_{{=it.oldEntity.title}};{{=it.separator}}",
        "createFieldTemplate": "ALTER TABLE {{=it.entity.title}} ADD COLUMN {{=it.field.name}} {{=it.field.type}} {{? it.field.notNull}}NOT NULL{{?}} {{? it.field.defaultValue}}DEFAULT {{? null==it.field.defaultValue}}NULL{{??}}'{{=it.field.defaultValue}}'{{?}}{{?}} {{? it.field.autoIncrement}}AUTO_INCREMENT{{?}} {{? it.field.pk}}PRIMARY KEY{{?}} {{? it.field.chnname}}COMMENT '{{=it.field.chnname}}'{{?}} {{? it.field.addAfter}}AFTER {{=it.field.addAfter}}{{?}};{{=it.separator}}",
        "updateFieldTemplate": "ALTER TABLE {{=it.entity.title}} MODIFY COLUMN {{=it.field.name}} {{=it.field.type}} {{? it.field.notNull}}NOT NULL{{?}} {{? it.field.defaultValue}}DEFAULT {{? null==it.field.defaultValue}}NULL{{??}}'{{=it.field.defaultValue}}'{{?}}{{?}} {{? it.field.autoIncrement}}AUTO_INCREMENT{{?}} {{? it.field.chnname}}COMMENT '{{=it.field.chnname}}'{{?}};{{=it.separator}}",
        "deleteFieldTemplate": "ALTER TABLE {{=it.entity.title}} DROP {{=it.field.name}};{{=it.separator}}",
        "deleteIndexTemplate": "ALTER TABLE {{=it.entity.title}} DROP INDEX {{=it.index.name}};{{=it.separator}}",
        "createIndexTemplate": "ALTER TABLE {{=it.entity.title}} ADD {{? it.index.isUnique}}UNIQUE{{??}}INDEX{{?}} {{=it.index.name}}({{=it.func.join(...it.index.fields,',')}});{{=it.separator}}",
        "updateTableComment": "ALTER TABLE {{=it.entity.title}} COMMENT '{{=it.entity.chnname}}';{{=it.separator}}"
      },
      {
        "code": "JAVA",
        "template": "package group.rober.pdman.{{=it.module.name}}.entity;\n$blankline\nimport javax.persistence.*;\nimport java.io.Serializable;\nimport java.util.Date;\n$blankline\n$blankline\n\n/** {{=it.entity.chnname}} */\n@Table(name=\"{{=it.entity.title}}\")\npublic class {{=it.func.camel(it.entity.title,true) }} implements Serializable,Cloneable{\n{{~it.entity.fields:field:index}}\n    /** {{=it.func.join(field.chnname,field.remark,';')}} */\n    {{? field.pk }}\n    @Id\n    @GeneratedValue\n    {{?}}\n    private {{=field.type}} {{=it.func.camel(field.name,false)}} ;\n{{~}}\n$blankline\n{{~it.entity.fields:field:index}}\n    /** {{=it.func.join(field.chnname,field.remark,';')}} */\n    public {{=field.type}} get{{=it.func.camel(field.name,true)}}(){\n        return this.{{=it.func.camel(field.name,false)}};\n    }\n    /** {{=it.func.join(field.chnname,field.remark,';')}} */\n    public void set{{=it.func.camel(field.name,true)}}({{=field.type}} {{= it.func.camel(field.name,false) }}){\n        this.{{=it.func.camel(field.name,false)}} = {{= it.func.camel(field.name,false) }};\n    }\n{{~}}\n}",
        "createTableTemplate": "package group.rober.pdman.{{=it.module.name}}.entity;\n$blankline\nimport javax.persistence.*;\nimport java.io.Serializable;\nimport java.util.Date;\n$blankline\n$blankline\n@Table(name=\"{{=it.entity.title}}\")\npublic class {{=it.func.camel(it.entity.title,true) }} implements Serializable,Cloneable{\n{{~it.entity.fields:field:index}}\n    /** {{=it.func.join(field.chnname,field.remark,';')}} */\n    {{? field.pk }}\n    @Id\n    @GeneratedValue\n    {{?}}\n    private {{=field.type}} {{=it.func.camel(field.name,false)}} ;\n{{~}}\n$blankline\n{{~it.entity.fields:field:index}}\n    /** {{=it.func.join(field.chnname,field.remark,';')}} */\n    public {{=field.type}} get{{=it.func.camel(field.name,true)}}(){\n        return this.{{=it.func.camel(field.name,false)}};\n    }\n    /** {{=it.func.join(field.chnname,field.remark,';')}} */\n    public void set{{=it.func.camel(field.name,true)}}({{=field.type}} {{= it.func.camel(field.name,false) }}){\n        this.{{=it.func.camel(field.name,false)}} = {{= it.func.camel(field.name,false) }};\n    }\n{{~}}\n}",
        "deleteTableTemplate": "",
        "rebuildTableTemplate": "",
        "createFieldTemplate": "",
        "updateFieldTemplate": "",
        "deleteFieldTemplate": "",
        "deleteIndexTemplate": "",
        "createIndexTemplate": "",
        "updateTableComment": ""
      }
    ]
  },
  "profile": {
    "dbs": [
      {
        "name": "security_pro",
        "defaultDB": false,
        "properties": {
          "driver_class_name": "com.mysql.jdbc.Driver",
          "url": "jdbc:mysql://10.175.205.136:3306/security?characterEncoding=UTF-8&useSSL=false&useUnicode=true&serverTimezone=UTC",
          "password": "Best2020",
          "username": "security"
        }
      },
      {
        "name": "security_dev",
        "defaultDB": true,
        "properties": {
          "driver_class_name": "com.mysql.jdbc.Driver",
          "url": "jdbc:mysql://127.0.0.1:3306/security?characterEncoding=UTF-8&useSSL=false&useUnicode=true&serverTimezone=UTC",
          "password": "123456",
          "username": "root"
        }
      }
    ]
  }
}